MANIFEST.in
README.md
VERSION
setup.py
kaching/__init__.py
kaching.egg-info/PKG-INFO
kaching.egg-info/SOURCES.txt
kaching.egg-info/dependency_links.txt
kaching.egg-info/entry_points.txt
kaching.egg-info/not-zip-safe
kaching.egg-info/top_level.txt
kaching/fail/Buzzer1.mp3
kaching/fail/Buzzer2.mp3
kaching/fail/DebbieDownerHorn1.mp3
kaching/fail/DebbieDownerHorn2.mp3
kaching/fail/Failure-WahWah.mp3
kaching/fail/FamilyFeud-Buzzer1.mp3
kaching/fail/FamilyFeud-Buzzer2.mp3
kaching/fail/FamilyFeud-Buzzer3.mp3
kaching/fail/Halloween-WitchCackle.mp3
kaching/fail/Laugh-Evil1.mp3
kaching/fail/Pacman-Die.mp3
kaching/fail/PressYourLuck-Whammy.mp3
kaching/fail/Sad-Trombone.mp3
kaching/fail/SadTrumpet-MutedWahWah.mp3
kaching/fail/ThePriceIsRight-LoserHorns.mp3
kaching/fail/VideoGame-DigDug-Dies.mp3
kaching/fail/Wheel-of-Fortune-Bankrupt.mp3
kaching/fail/Wheel-of-Fortune-Buzzer.mp3
kaching/fail/clown-honk.mp3
kaching/fail/foghorn.mp3
kaching/pass/CashRegister.mp3
kaching/pass/FamilyFeud-Bell.mp3
kaching/pass/GameshowBellDing1.mp3
kaching/pass/GameshowBellDing2.mp3
kaching/pass/GameshowBellDing3.mp3
kaching/pass/GameshowBellDing4.mp3
kaching/pass/Pacman-PowerPill.mp3
kaching/pass/SuperMarioBrothers-1upExtraLife.mp3
kaching/pass/SuperMarioBrothers-Coin.mp3
kaching/pass/SuperMarioBrothers-ExtraLife.mp3
kaching/pass/SuperMarioBrothers-GoingDownPipe.mp3
kaching/pass/cash-register2.mp3
kaching/start/Gun-Barrett50Caliber-Cocking1.mp3
kaching/start/ShotGun-Cocking.mp3
kaching/start/WhipCrack-Short.mp3
kaching/start/WhipCrack.mp3